[{"success": 2, "all": 2, "fail": 0, "skip": 0, "error": 0, "runtime": "30.635986 S", "begin_time": "2023-10-20 18:55:26", "pass_rate": "100.00"}, {"success": 2, "all": 2, "fail": 0, "skip": 0, "error": 0, "runtime": "30.088215 S", "begin_time": "2023-10-20 18:59:20", "pass_rate": "100.00"}, {"success": 1, "all": 2, "fail": 1, "skip": 0, "error": 0, "runtime": "29.553852 S", "begin_time": "2023-10-20 19:00:22", "pass_rate": "50.00"}, {"success": 1, "all": 2, "fail": 1, "skip": 0, "error": 0, "runtime": "33.680100 S", "begin_time": "2023-10-20 19:38:42", "pass_rate": "50.00"}, {"success": 1, "all": 2, "fail": 1, "skip": 0, "error": 0, "runtime": "30.683683 S", "begin_time": "2023-10-20 19:42:03", "pass_rate": "50.00"}, {"success": 0, "all": 2, "fail": 2, "skip": 0, "error": 0, "runtime": "14.363403 S", "begin_time": "2023-10-20 19:42:50", "pass_rate": "0.00"}, {"success": 2, "all": 2, "fail": 0, "skip": 0, "error": 0, "runtime": "30.945197 S", "begin_time": "2023-10-20 20:10:30", "pass_rate": "100.00"}, {"success": 2, "all": 2, "fail": 0, "skip": 0, "error": 0, "runtime": "28.716359 S", "begin_time": "2023-10-20 20:12:19", "pass_rate": "100.00"}, {"success": 2, "all": 2, "fail": 0, "skip": 0, "error": 0, "runtime": "32.815953 S", "begin_time": "2023-10-21 15:01:03", "pass_rate": "100.00"}, {"success": 2, "all": 2, "fail": 0, "skip": 0, "error": 0, "runtime": "32.009956 S", "begin_time": "2023-10-21 15:10:57", "pass_rate": "100.00"}, {"success": 2, "all": 2, "fail": 0, "skip": 0, "error": 0, "runtime": "33.222287 S", "begin_time": "2023-10-23 08:40:32", "pass_rate": "100.00"}, {"success": 2, "all": 2, "fail": 0, "skip": 0, "error": 0, "runtime": "28.612995 S", "begin_time": "2023-10-23 08:42:08", "pass_rate": "100.00"}, {"success": 2, "all": 2, "fail": 0, "skip": 0, "error": 0, "runtime": "27.889076 S", "begin_time": "2023-10-23 08:43:52", "pass_rate": "100.00"}, {"success": 1, "all": 2, "fail": 1, "skip": 0, "error": 0, "runtime": "28.228483 S", "begin_time": "2023-10-23 08:48:20", "pass_rate": "50.00"}, {"success": 1, "all": 2, "fail": 1, "skip": 0, "error": 0, "runtime": "28.209954 S", "begin_time": "2023-10-23 08:51:31", "pass_rate": "50.00"}, {"success": 1, "all": 2, "fail": 1, "skip": 0, "error": 0, "runtime": "27.202753 S", "begin_time": "2023-10-23 08:55:13", "pass_rate": "50.00"}, {"success": 1, "all": 2, "fail": 1, "skip": 0, "error": 0, "runtime": "30.008787 S", "begin_time": "2023-10-23 09:42:58", "pass_rate": "50.00"}, {"success": 0, "all": 1, "fail": 0, "skip": 1, "error": 0, "runtime": "0.00 S", "begin_time": "2023-10-23 11:38:51", "pass_rate": "0.00"}, {"success": 0, "all": 1, "fail": 0, "skip": 1, "error": 0, "runtime": "0.00 S", "begin_time": "2023-10-23 11:42:24", "pass_rate": "0.00"}, {"success": 0, "all": 1, "fail": 0, "skip": 1, "error": 0, "runtime": "0.00 S", "begin_time": "2023-10-23 11:42:54", "pass_rate": "0.00"}, {"success": 0, "all": 1, "fail": 0, "skip": 1, "error": 0, "runtime": "0.00 S", "begin_time": "2023-10-23 11:43:14", "pass_rate": "0.00"}, {"success": 1, "all": 2, "fail": 1, "skip": 0, "error": 0, "runtime": "27.486196 S", "begin_time": "2023-10-23 15:16:06", "pass_rate": "50.00"}, {"success": 1, "all": 2, "fail": 1, "skip": 0, "error": 0, "runtime": "30.824971 S", "begin_time": "2023-10-23 16:43:26", "pass_rate": "50.00"}]